waggle/__init__.py
waggle/data/__init__.py
waggle/data/audio.py
waggle/data/data_shim.py
waggle/data/measurements.py
waggle/data/timestamp.py
waggle/data/vision.py
waggle/plugin/__init__.py
waggle/plugin/config.py
waggle/plugin/plugin.py
waggle/plugin/rabbitmq.py
waggle/plugin/time.py
waggle/plugin/uploader.py
pywaggle-0.56.3.dist-info/METADATA
pywaggle-0.56.3.dist-info/WHEEL
pywaggle-0.56.3.dist-info/top_level.txt
pywaggle-0.56.3.dist-info/RECORD
