Metadata-Version: 2.4
Name: pywaggle
Version: 0.56.3
Summary: Official Waggle Python module.
Home-page: https://github.com/waggle-sensor/pywaggle
Author: Sean Shahkarami
Author-email: sean.shahkarami@gmail.com
License: "BSD 3-clause"
Project-URL: Bug Tracker, https://github.com/waggle-sensor/pywaggle/issues
Classifier: Programming Language :: Python :: 3
Classifier: Programming Language :: Python :: 3.6
Classifier: Programming Language :: Python :: 3.7
Classifier: Programming Language :: Python :: 3.8
Classifier: Programming Language :: Python :: 3.9
Classifier: License :: OSI Approved :: BSD License
Classifier: Operating System :: OS Independent
Requires-Python: >=3.6
Requires-Dist: pika>=1.2.0
Requires-Dist: pywagglemsg>=0.4.0
Provides-Extra: audio
Requires-Dist: numpy>=1.18.0; extra == "audio"
Requires-Dist: soundcard>=0.4.1; extra == "audio"
Requires-Dist: soundfile>=0.9.0; extra == "audio"
Provides-Extra: vision
Requires-Dist: numpy>=1.18.0; extra == "vision"
Requires-Dist: opencv-python>=4.5.0; extra == "vision"
Requires-Dist: ffmpeg-python>=0.2.0; extra == "vision"
Provides-Extra: all
Requires-Dist: numpy>=1.18.0; extra == "all"
Requires-Dist: soundcard>=0.4.1; extra == "all"
Requires-Dist: soundfile>=0.9.0; extra == "all"
Requires-Dist: opencv-python>=4.5.0; extra == "all"
Requires-Dist: ffmpeg-python>=0.2.0; extra == "all"
